AUTHORS.md
MANIFEST.in
README.rst
requirements.txt
runtests.py
setup.py
Shake_SQLAlchemy.egg-info/PKG-INFO
Shake_SQLAlchemy.egg-info/SOURCES.txt
Shake_SQLAlchemy.egg-info/dependency_links.txt
Shake_SQLAlchemy.egg-info/not-zip-safe
Shake_SQLAlchemy.egg-info/requires.txt
Shake_SQLAlchemy.egg-info/top_level.txt
shake_sqlalchemy/__init__.py
shake_sqlalchemy/query.py
shake_sqlalchemy/serializers.py
shake_sqlalchemy/types.py
tests/__init__.py
tests/test_sqlalchemy.py