Metadata-Version: 1.0
Name: Shake-SQLAlchemy
Version: 1.0.1
Summary: Add SQLAlchemy support to your Shake application
Home-page: http://github.com/lucuma/Shake
Author: Juan-Pablo Scaletti
Author-email: juanpablo@lucumalabs.com
License: MIT license (http://www.opensource.org/licenses/mit-license.php)
Platform: UNKNOWN
Classifier: Development Status :: 4 - Beta
Classifier: Environment :: Web Environment
Classifier: Intended Audience :: Developers
Classifier: License :: OSI Approved :: MIT License
Classifier: Operating System :: OS Independent
Classifier: Programming Language :: Python
Classifier: Topic :: Internet :: WWW/HTTP :: Dynamic Content
Classifier: Topic :: Software Development :: Libraries :: Python Modules
